imgpt/__init__.py
imgpt/cli.py
imgpt-0.2.0.dist-info/LICENSE
imgpt-0.2.0.dist-info/METADATA
imgpt-0.2.0.dist-info/WHEEL
imgpt-0.2.0.dist-info/entry_points.txt
imgpt-0.2.0.dist-info/RECORD
