Metadata-Version: 2.3
Name: imgpt
Version: 0.2.0
Summary: AI Image Generator - Generate images using OpenAI API from prompt files or direct input
Author: Jacob Valdez
Author-email: jacobfv123@gmail.com
Requires-Python: >=3.12
Classifier: Programming Language :: Python :: 3
Classifier: Programming Language :: Python :: 3.12
Classifier: Programming Language :: Python :: 3.13
Requires-Dist: openai (>=1.82.0,<2.0.0)
